zhconv_rs-0.3.3.dist-info/METADATA
zhconv_rs-0.3.3.dist-info/WHEEL
zhconv_rs.libs/libgcc_s-1e52349c.so.1
zhconv_rs/__init__.py
zhconv_rs/__init__.pyi
zhconv_rs/py.typed
zhconv_rs/zhconv_rs.abi3.so
zhconv_rs-0.3.3.dist-info/RECORD
